mcsq/__init__.py
mcsq/driver.py
mcsq/py.typed
mcsq/tests/__init__.py
mcsq-0.0.0.dev1.dist-info/LICENSE
mcsq-0.0.0.dev1.dist-info/METADATA
mcsq-0.0.0.dev1.dist-info/WHEEL
mcsq-0.0.0.dev1.dist-info/top_level.txt
mcsq-0.0.0.dev1.dist-info/RECORD
